FormulaLab/__init__.py
FormulaLab/ftools.py
FormulaLab/search.py
FormulaLab/test_search.py
FormulaLab-0.1.0.dist-info/LICENSE
FormulaLab-0.1.0.dist-info/METADATA
FormulaLab-0.1.0.dist-info/WHEEL
FormulaLab-0.1.0.dist-info/top_level.txt
FormulaLab-0.1.0.dist-info/RECORD
