Metadata-Version: 2.1
Name: FormulaLab
Version: 0.1.0
Summary: Search Engine of Mathmatical Formulas Database
Home-page: https://azizalqasem.github.io/FormulaLab/index.html
Author: Abdulaziz Alqasem
Author-email: Aziz_Alqasem@hotmail.com
License: UNKNOWN
Project-URL: Documentation, https://azizalqasem.github.io/FormulaLab/index.html
Project-URL: Source, https://github.com/AzizAlqasem/FormulaLab
Keywords: FormulaLab,Formulas Search Engine,Deriving Formulas,Formulas,Search,derivation,database,math,physics,Science,Engineering,Solving equations,equations,Formula,Scientific Research
Platform: UNKNOWN
Classifier: Programming Language :: Python :: 3
Classifier: License :: OSI Approved :: MIT License
Classifier: Development Status :: 5 - Production/Stable
Classifier: Operating System :: OS Independent
Classifier: Intended Audience :: Science/Research
Classifier: Intended Audience :: Developers
Classifier: Intended Audience :: Education
Classifier: Topic :: Database
Classifier: Topic :: Documentation :: Sphinx
Classifier: Topic :: Scientific/Engineering
Classifier: Topic :: Scientific/Engineering :: Mathematics
Classifier: Topic :: Scientific/Engineering :: Physics
Requires-Python: >=3.4
Requires-Dist: sympy
Requires-Dist: pandas
Requires-Dist: numpy
